dothttp_insomnia_importer/__main__.py
dothttp_insomnia_importer/insomnia.py
dothttp_insomnia_importer/loader.py
dothttp_insomnia_importer/utils.py
dothttp_insomnia_importer-0.1.0.dist-info/LICENSE
dothttp_insomnia_importer-0.1.0.dist-info/METADATA
dothttp_insomnia_importer-0.1.0.dist-info/WHEEL
dothttp_insomnia_importer-0.1.0.dist-info/entry_points.txt
dothttp_insomnia_importer-0.1.0.dist-info/RECORD
