Metadata-Version: 2.1
Name: dothttp_insomnia_importer
Version: 0.1.0
Summary: 
License: MIT
Author: Prasanth
Author-email: kesavarapu.siva@gmail.com
Requires-Python: >=3.10,<3.13
Classifier: License :: OSI Approved :: MIT License
Classifier: Programming Language :: Python :: 3
Classifier: Programming Language :: Python :: 3.10
Classifier: Programming Language :: Python :: 3.11
Classifier: Programming Language :: Python :: 3.12
Requires-Dist: dothttp-req (==0.0.43a10)
